kubedeployer/__init__.py
kubedeployer/__main__.py
kubedeployer/deploy.py
kubedeployer/docker.py
kubedeployer/files.py
kubedeployer/kubectl.py
kubedeployer/kustomize.py
kubedeployer/manifests.py
kubedeployer/text.py
kubedeployer/types.py
kubedeployer/console/__init__.py
kubedeployer/console/wrap.py
kubedeployer/deployer/__init__.py
kubedeployer/deployer/abstract_deployer.py
kubedeployer/deployer/kustomize_deployer.py
kubedeployer/deployer/orthodox_deployer.py
kubedeployer/deployer/smart_deployer.py
kubedeployer/gitlab_ci/__init__.py
kubedeployer/gitlab_ci/environment_variables.py
kubedeployer/gitlab_ci/exceptions.py
kubedeployer/gitlab_ci/specification.py
kubedeployer/gitlab_ci/variable_reader.py
kubedeployer/gitlab_ci/variable_types.py
kubedeployer/k8s/__init__.py
kubedeployer/k8s/annotations.py
kubedeployer/k8s/deserialize.py
kubedeployer/k8s/models.py
kubedeployer/k8s/specifications.py
kubedeployer/security/__init__.py
kubedeployer/security/kubesec/__init__.py
kubedeployer/security/kubesec/data.py
kubedeployer/security/kubesec/errors.py
kubedeployer/security/kubesec/formatters.py
kubedeployer/security/kubesec/report.py
kubedeployer/security/kubesec/scanner.py
kubedeployer/security/trivy/__init__.py
kubedeployer/security/trivy/data.py
kubedeployer/security/trivy/errors.py
kubedeployer/security/trivy/formatters.py
kubedeployer/security/trivy/report.py
kubedeployer/security/trivy/scanner.py
kubedeployer/utils/__init__.py
kubedeployer/utils/convert.py
kubedeployer/vault/__init__.py
kubedeployer/vault/client.py
kubedeployer/vault/factory.py
kubedeployer/vault/service.py
kubedeployer-1.2.9.dist-info/METADATA
kubedeployer-1.2.9.dist-info/WHEEL
kubedeployer-1.2.9.dist-info/entry_points.txt
kubedeployer-1.2.9.dist-info/licenses/LICENSE
kubedeployer-1.2.9.dist-info/RECORD
