Metadata-Version: 2.1
Name: kubedeployer
Version: 1.2.9
Summary: package to deploy application on kubernetes
Project-URL: Homepage, https://github.com/itlabsio/kubedeployer
Project-URL: Bug Tracker, https://github.com/itlabsio/kubedeployer/issues
License:                                  Apache License
License-File: LICENSE
Keywords: deploy,kubernetes
Classifier: License :: OSI Approved :: Apache Software License
Classifier: Operating System :: OS Independent
Classifier: Programming Language :: Python :: 3
Requires-Python: >=3.10
Requires-Dist: hvac==0.8.2
Requires-Dist: kubernetes==25.3.0
Requires-Dist: prettytable==2.5.0
Requires-Dist: pydantic==1.10.2
Requires-Dist: python-dotenv==1.0.0
Requires-Dist: pyyaml==6.0.1
Requires-Dist: ujson==5.4.0
